{"make":"07823622b82ab4bd","models":[{"name":"038482d7069bfc32","types":[{"name":"0d2f6cc1bf3dd4f8e604e3a050dc7d01","fluids":[{"n":"Teana 2.5 16V AWD (2008-2014)","c":"QR25DE","i":"Normal (preferred)","p":"1111122","ic":"💧","pc":"Engine"}]},{"name":"477911c1d6359bcaffcd5c2610b4184f","fluids":[{"n":"Teana 2.5 V6 (2008-2014)","c":"VQ25DE","i":"Normal (preferred)","p":"1111122","ic":"💧","pc":"Engine"}]},{"name":"4ace44c39b8f2e1d","fluids":[{"n":"Teana 2.5 V6 (2008-2014)","c":"VQ25DE","i":"Normal (preferred)","p":"1111122","ic":"💧","pc":"Engine"}]},{"name":"67003bd20a696591","fluids":[{"n":"Teana 3.5 V6 (2008-2014)","c":"VQ35DE","i":"Normal (preferred)","p":"1111122","ic":"💧","pc":"Engine"}]},{"name":"b96db9c22030d3a020b7ca03e98014f1","fluids":[{"n":"Teana 3.5 V6 (2008-2014)","c":"VQ35DE","i":"Normal (preferred)","p":"1111122","ic":"💧","pc":"Engine"}]},{"name":"bda58c9e0487579a","fluids":[{"n":"Teana 2.5 16V AWD (2008-2014)","c":"QR25DE","i":"Normal (preferred)","p":"1111122","ic":"💧","pc":"Engine"}]}]},{"name":"1fe790e9ec2e7ba3","types":[{"name":"12c90611c6a1fcba793212530195e7ee","fluids":[{"n":"Teana 3.5 (2014- )","c":"VQ35DE","i":"Normal (preferred)","p":"1111122","ic":"💧","pc":"Engine"}]},{"name":"1c86ad0a317700e6969d061b8e79a4ad","fluids":[{"n":"Teana 2.5 (2014- )","c":"QR25DE","i":"Normal (preferred)","p":"1111122","ic":"💧","pc":"Engine"}]},{"name":"ab08d14c9a282f22","fluids":[{"n":"Teana 2.5 (2014- )","c":"QR25DE","i":"Normal (preferred)","p":"1111122","ic":"💧","pc":"Engine"}]},{"name":"cec5074f2d611edb","fluids":[{"n":"Teana 3.5 (2014- )","c":"VQ35DE","i":"Normal (preferred)","p":"1111122","ic":"💧","pc":"Engine"}]}]},{"name":"382d6c18e7b80ee2","types":[{"name":"58c2749ab8bb140316743289d45a0114","fluids":[{"n":"Sentra 1.6 (2014- )","c":"HR16DE","i":"Normal (preferred)","p":"1111122","ic":"💧","pc":"Engine"}]},{"name":"fe8736d360eee5d9","fluids":[{"n":"Sentra 1.6 (2014- )","c":"HR16DE","i":"Normal (preferred)","p":"1111122","ic":"💧","pc":"Engine"}]}]},{"name":"48080df09a78f040","types":[{"name":"350f668a19c45299","fluids":[{"n":"Almera Classic 1.6 (2006-2012)","c":"QG16DE","i":"Normal","p":"1111110","ic":"💧","pc":"Engine"}]},{"name":"91e2ba04a20628f000047251ccfe7593","fluids":[{"n":"Almera Classic 1.6 (2006-2012)","c":"QG16DE","i":"Normal","p":"1111110","ic":"💧","pc":"Engine"}]}]},{"name":"52221a86e2894e66","types":[{"name":"0b8ecaeb79831908c20ffd8973042ad5","fluids":[{"n":"Terrano 1.6 AWD (2014- )","c":"K4M","i":"Normal","p":"1111145","ic":"💧","pc":"Engine"}]},{"name":"884e74ebe6b9a406","fluids":[{"n":"Terrano 1.6 AWD (2014- )","c":"K4M","i":"Normal","p":"1111145","ic":"💧","pc":"Engine"}]},{"name":"a090952edafe7f50d8b0bfdb862a63ff","fluids":[{"n":"Terrano 1.6 (2014- )","c":"K4M","i":"Normal","p":"1111145","ic":"💧","pc":"Engine"}]},{"name":"b69d9aca38f75bba0f763417147dddcf","fluids":[{"n":"Terrano 2.0 AWD (2014- )","c":"F4R","i":"Normal","p":"1111145","ic":"💧","pc":"Engine"}]},{"name":"d1d6fc95451cc37a","fluids":[{"n":"Terrano 2.0 AWD (2014- )","c":"F4R","i":"Normal","p":"1111145","ic":"💧","pc":"Engine"}]},{"name":"f2643219fca20cde","fluids":[{"n":"Terrano 1.6 (2014- )","c":"K4M","i":"Normal","p":"1111145","ic":"💧","pc":"Engine"}]}]},{"name":"577e1473718628dc","types":[{"name":"3f64920c4f926145","fluids":[{"n":"Patrol 5.6 V8 (298 kW) (2015- )","c":"VK56VD","i":"Normal (preferred)","p":"1111109","ic":"💧","pc":"Engine"}]},{"name":"5c1657342c0036b3dad7a1acf67da77e","fluids":[{"n":"Patrol 5.6 V8 (298 kW) (2012-2015)","c":"VK56VD","i":"Normal (preferred)","p":"1111122","ic":"💧","pc":"Engine"}]},{"name":"616576fed84bb953","fluids":[{"n":"Patrol 5.6 V8 (298 kW) (2012-2015)","c":"VK56VD","i":"Normal (preferred)","p":"1111122","ic":"💧","pc":"Engine"}]},{"name":"866e1e7c005018b0","fluids":[{"n":"Patrol 5.6 V8 (298 kW) (2010-2012)","c":"VK56VD","i":"Normal (preferred)","p":"1111122","ic":"💧","pc":"Engine"}]},{"name":"8cc0ee7956ec706d6e18c9884ee2ccc8","fluids":[{"n":"Patrol 5.6 V8 (298 kW) (2010-2012)","c":"VK56VD","i":"Normal (preferred)","p":"1111122","ic":"💧","pc":"Engine"}]},{"name":"97539628da7cb916648b05208a722704","fluids":[{"n":"Patrol 5.6 V8 (298 kW) (2015- )","c":"VK56VD","i":"Normal (preferred)","p":"1111109","ic":"💧","pc":"Engine"}]}]},{"name":"5a14de207326d312","types":[{"name":"0af67192d35148db48bfc1392206b5b5","fluids":[{"n":"Pathfinder Hybrid (2014- )","c":"QR25DER","i":"Normal (preferred)","p":"1111109","ic":"💧","pc":"Engine"}]},{"name":"380a71373527f1eb","fluids":[{"n":"Pathfinder 3.5 V6 (2014- )","c":"VQ35DE","i":"Normal (preferred)","p":"1111122","ic":"💧","pc":"Engine"}]},{"name":"8b33450b77ae32f7","fluids":[{"n":"Pathfinder Hybrid (2014- )","c":"QR25DER","i":"Normal (preferred)","p":"1111109","ic":"💧","pc":"Engine"}]},{"name":"9950fb1d97416559de22578a3bde5b79","fluids":[{"n":"Pathfinder 3.5 V6 (2014- )","c":"VQ35DE","i":"Normal (preferred)","p":"1111122","ic":"💧","pc":"Engine"}]}]},{"name":"638e5b0df7bd0c0c","types":[{"name":"06c632886354e6f88f686b8cfc7d5e85","fluids":[{"n":"Qashqai 1.2 DIG-T (2014- )","c":"HRA2DDT","i":"Normal (preferred)","p":"1111136","ic":"💧","pc":"Engine"}]},{"name":"2fbc37e8538fa4e5","fluids":[{"n":"Qashqai 1.6 dCi DPF (2014- )","c":"R9M","i":"Normal","p":"1111121","ic":"💧","pc":"Engine"}]},{"name":"2ff594688d9f5b1ffce33e024ff8a9d0","fluids":[{"n":"Qashqai 2.0 (2014- )","c":"MR20DD","i":"Normal (preferred)","p":"1111122","ic":"💧","pc":"Engine"}]},{"name":"328d609779cd35f3","fluids":[{"n":"Qashqai 1.2 DIG-T (2014- )","c":"HRA2DDT","i":"Normal (preferred)","p":"1111136","ic":"💧","pc":"Engine"}]},{"name":"3622f449bf1b7a53","fluids":[{"n":"Qashqai 2.0 AWD (2014- )","c":"MR20DD","i":"Normal (preferred)","p":"1111122","ic":"💧","pc":"Engine"}]},{"name":"3a3b75cfe7b1d3953456286332e4547c","fluids":[{"n":"Qashqai 1.6 dCi DPF (2014- )","c":"R9M","i":"Normal","p":"1111121","ic":"💧","pc":"Engine"}]},{"name":"3d7925c2848f8fe93ec1e4179b2acb0d","fluids":[{"n":"Qashqai 2.0 AWD (2014- )","c":"MR20DD","i":"Normal (preferred)","p":"1111122","ic":"💧","pc":"Engine"}]},{"name":"d1ca525996fe4d9a","fluids":[{"n":"Qashqai 2.0 (2014- )","c":"MR20DD","i":"Normal (preferred)","p":"1111122","ic":"💧","pc":"Engine"}]}]},{"name":"670f07078bec89d8","types":[{"name":"0fcad1928f42d44c","fluids":[{"n":"Murano 3.5 V6 (2016- )","c":"VQ35DE","i":"Normal (preferred)","p":"1111122","ic":"💧","pc":"Engine"}]},{"name":"3f632713b5ac7226","fluids":[{"n":"Murano Hybrid (2016- )","c":"QR25DER","i":"Normal (preferred)","p":"1111109","ic":"💧","pc":"Engine"}]},{"name":"72112435ef62190344140a97a716c038","fluids":[{"n":"Murano Hybrid (2016- )","c":"QR25DER","i":"Normal (preferred)","p":"1111109","ic":"💧","pc":"Engine"}]},{"name":"b4c4c3b54cf8d12393f723796c0c3832","fluids":[{"n":"Murano 3.5 V6 (2016- )","c":"VQ35DE","i":"Normal (preferred)","p":"1111122","ic":"💧","pc":"Engine"}]}]},{"name":"c34f65e4f6634953","types":[{"name":"eb8bf6eb957efeea","fluids":[{"n":"Almera 1.6 (2013- )","c":"K4M","i":"Normal","p":"1111145","ic":"💧","pc":"Engine"}]},{"name":"f418f96cd4dc71c7affa9927f93e8bdc","fluids":[{"n":"Almera 1.6 (2013- )","c":"K4M","i":"Normal","p":"1111145","ic":"💧","pc":"Engine"}]}]},{"name":"fdac0098d11dfa10","types":[{"name":"02bbee1deffc25ef","fluids":[{"n":"Pulsar / Tiida 1.6 (2014- )","c":"HR16DE","i":"Normal (preferred)","p":"1111122","ic":"💧","pc":"Engine"}]},{"name":"ffd3b5a8ffb3eab8e9c6895ba9cf2fd3","fluids":[{"n":"Pulsar / Tiida 1.6 (2014- )","c":"HR16DE","i":"Normal (preferred)","p":"1111122","ic":"💧","pc":"Engine"}]}]},{"name":"ff2b3645949a1cf4","types":[{"name":"04f08e77367fb92f","fluids":[{"n":"X-Trail 1.6 dCi 130 AWD DPF (2014- )","c":"R9M","i":"Normal","p":"1111121","ic":"💧","pc":"Engine"}]},{"name":"10ca7a67cbec11bb","fluids":[{"n":"X-Trail 2.0 (2014- )","c":"MR20DD","i":"Normal (preferred)","p":"1111122","ic":"💧","pc":"Engine"}]},{"name":"4ed9b31b72cbe75c","fluids":[{"n":"X-Trail 2.5 AWD (2014- )","c":"QR25DE","i":"Normal (preferred)","p":"1111122","ic":"💧","pc":"Engine"}]},{"name":"65f491e90b2fdea3e48194527c2ebf30","fluids":[{"n":"X-Trail 2.0 AWD (2014- )","c":"MR20DD","i":"Normal (preferred)","p":"1111122","ic":"💧","pc":"Engine"}]},{"name":"7c4611bc35345465d0cbe12ebf87bcdd","fluids":[{"n":"X-Trail 2.5 AWD (2014- )","c":"QR25DE","i":"Normal (preferred)","p":"1111122","ic":"💧","pc":"Engine"}]},{"name":"81981c8adb862f33b096019e65d61d8d","fluids":[{"n":"X-Trail 1.6 dCi 130 AWD DPF (2014- )","c":"R9M","i":"Normal","p":"1111121","ic":"💧","pc":"Engine"}]},{"name":"a8efe446dd861f25c983f2691ecb8123","fluids":[{"n":"X-Trail 2.0 (2014- )","c":"MR20DD","i":"Normal (preferred)","p":"1111122","ic":"💧","pc":"Engine"}]},{"name":"f15003325b37f437","fluids":[{"n":"X-Trail 2.0 AWD (2014- )","c":"MR20DD","i":"Normal (preferred)","p":"1111122","ic":"💧","pc":"Engine"}]}]}]}