{"make":"8868192236ce720c","models":[{"name":"3bb19480b4063512","types":[{"name":"16ce15eb8597e307","fluids":[{"n":"Sorento 2.4 MPI 4WD (2014-2020)","c":"G4KE","i":"Normal","p":"1111110","ic":"💧","pc":"Engine"}]},{"name":"52a02d85253407cfba1a8af7e31d2e47","fluids":[{"n":"Sorento 2.4 MPI 4WD (2014-2020)","c":"G4KE","i":"Normal","p":"1111110","ic":"💧","pc":"Engine"}]}]},{"name":"41a398029fce655f","types":[{"name":"16a9bb5212bb583a","fluids":[{"n":"Rio 1.4 Kappa MPI (2017- )","c":"G4LC","i":"Normal","p":"1111110","ic":"💧","pc":"Engine"}]},{"name":"27a0f29093425915","fluids":[{"n":"Rio 1.6 Gamma MPI (2017- )","c":"G4FG","i":"Normal","p":"1111110","ic":"💧","pc":"Engine"}]},{"name":"2b4fe1ae5bd12ec9","fluids":[{"n":"Rio 1.4 Kappa MPI X-Line  (2017- )","c":"G4LC","i":"Normal","p":"1111110","ic":"💧","pc":"Engine"}]},{"name":"3a1744a74a83034958ba8e26f93e26bb","fluids":[{"n":"Rio 1.6 Gamma MPI  (2017- )","c":"G4FG","i":"Normal","p":"1111110","ic":"💧","pc":"Engine"},{"n":"Rio 1.6 Gamma MPI (2017- )","c":"G4FG","i":"Normal","p":"1111110","ic":"💧","pc":"Engine"}]},{"name":"40036358b7c7b0f6b8c6b59b1e936b3f","fluids":[{"n":"Rio 1.4 Kappa MPI X-Line (2017- )","c":"G4LC","i":"Normal","p":"1111110","ic":"💧","pc":"Engine"}]},{"name":"71d587bc40b9b26f","fluids":[{"n":"Rio 1.6 Gamma MPI X-Line (2017- )","c":"G4FG","i":"Normal","p":"1111110","ic":"💧","pc":"Engine"}]},{"name":"d2df5d4e46b66f27f5ea1be8b43faad1","fluids":[{"n":"Rio 1.6 Gamma MPI X-Line (2017- )","c":"G4FG","i":"Normal","p":"1111110","ic":"💧","pc":"Engine"}]},{"name":"e83f88a3e5209166b3c083d1c9b77003","fluids":[{"n":"Rio 1.4 Kappa MPI (2017- )","c":"G4LC","i":"Normal","p":"1111110","ic":"💧","pc":"Engine"}]}]},{"name":"6d87f5d96cea9844","types":[{"name":"ac13c7bd4f10aeb23fa8ae856aa787ed","fluids":[{"n":"Optima 2.0 MPI (2018-2020)","c":"G4NA","i":"Normal","p":"1111110","ic":"💧","pc":"Engine"}]},{"name":"f942041b89052d2b","fluids":[{"n":"Optima 2.0 MPI (2018-2020)","c":"G4NA","i":"Normal","p":"1111110","ic":"💧","pc":"Engine"}]}]},{"name":"aefb53091e083e88","types":[{"name":"4412cf735276a84fcaa09704e1d11fee","fluids":[{"n":"Cerato 1.6 MPI (2016-2018)","c":"G4FG","i":"Normal","p":"1111108","ic":"💧","pc":"Engine"}]},{"name":"480b7edcdf064cbe5577b02ce9edb535","fluids":[{"n":"Cerato 1.6 MPI (2012-2016)","c":"G4FG","i":"Normal","p":"1111108","ic":"💧","pc":"Engine"}]},{"name":"55e7e5e7947a1be6","fluids":[{"n":"Cerato 1.6 MPI (2012-2016)","c":"G4FG","i":"Normal","p":"1111108","ic":"💧","pc":"Engine"}]},{"name":"d9807f175d343f48","fluids":[{"n":"Cerato 1.6 MPI (2016-2018)","c":"G4FG","i":"Normal","p":"1111108","ic":"💧","pc":"Engine"}]}]},{"name":"c224475a7c9a07f2","types":[{"name":"278fe785f7aaf6a47d4ead71d68c6a3d","fluids":[{"n":"Rio 1.4 CVVT (2014-2017)","c":"G4FA","i":"Normal","p":"1111110","ic":"💧","pc":"Engine"}]},{"name":"43f4b5bf16064be338fe9f4f661d3745","fluids":[{"n":"Rio 1.4 Gamma MPI (2015-2017)","c":"G4FA","i":"Normal","p":"1111110","ic":"💧","pc":"Engine"}]},{"name":"5f6863c58b4217bb","fluids":[{"n":"Rio 1.4 CVVT (2011-2014)","c":"G4FA","i":"Normal","p":"1111110","ic":"💧","pc":"Engine"}]},{"name":"6eb68dfdbfe8d9c0","fluids":[{"n":"Rio 1.6 CVVT (2014-2017)","c":"G4FC","i":"Normal","p":"1111110","ic":"💧","pc":"Engine"}]},{"name":"82efeb404ff732ef8be7bfbc91437381","fluids":[{"n":"Rio 1.4 CVVT (2011-2014)","c":"G4FA","i":"Normal","p":"1111110","ic":"💧","pc":"Engine"}]},{"name":"9a2378c1c40925921d3b931f102d4d52","fluids":[{"n":"Rio 1.6 CVVT (2011-2014)","c":"G4FC","i":"Normal","p":"1111110","ic":"💧","pc":"Engine"}]},{"name":"a3996dd69a087405","fluids":[{"n":"Rio 1.6 CVVT (2011-2014)","c":"G4FC","i":"Normal","p":"1111110","ic":"💧","pc":"Engine"}]},{"name":"c0fe07b55c11ae058d0e777e97a8a14f","fluids":[{"n":"Rio 1.6 Gamma MPI (2015-2017)","c":"G4FC","i":"Normal","p":"1111110","ic":"💧","pc":"Engine"}]},{"name":"c7edf303cb534437d23b31e07c71730d","fluids":[{"n":"Rio 1.6 CVVT (2014-2017)","c":"G4FC","i":"Normal","p":"1111110","ic":"💧","pc":"Engine"}]},{"name":"da9a33ad051b70f7","fluids":[{"n":"Rio 1.4 Gamma MPI (2015-2017)","c":"G4FA","i":"Normal","p":"1111110","ic":"💧","pc":"Engine"}]},{"name":"e7906ddf23782e8d","fluids":[{"n":"Rio 1.4 CVVT (2014-2017)","c":"G4FA","i":"Normal","p":"1111110","ic":"💧","pc":"Engine"}]},{"name":"f9653c5e5b7949c0","fluids":[{"n":"Rio 1.6 Gamma MPI (2015-2017)","c":"G4FC","i":"Normal","p":"1111110","ic":"💧","pc":"Engine"}]}]},{"name":"cb126988803860be","types":[{"name":"194bef110d8beb9e","fluids":[{"n":"Seltos 1.6 MPI AWD (2020- )","c":"G4FG","i":"Normal","p":"1111110","ic":"💧","pc":"Engine"}]},{"name":"316844815e8c3a472edaed8c1051004a","fluids":[{"n":"Seltos 1.6 MPI AWD (2020- )","c":"G4FG","i":"Normal","p":"1111110","ic":"💧","pc":"Engine"}]}]},{"name":"d6d4e175c3fc627a","types":[{"name":"2187438a4c9706c4","fluids":[{"n":"Soul 1.6 MPI (2019- )","c":"G4FG","i":"Normal","p":"1111110","ic":"💧","pc":"Engine"}]},{"name":"434c3efde0e5fb31","fluids":[{"n":"Soul 2.0 MPI (2019- )","c":"G4NA","i":"Normal","p":"1111110","ic":"💧","pc":"Engine"}]},{"name":"9f373590869786149d61c0c97b700219","fluids":[{"n":"Soul 1.6 MPI (2019- )","c":"G4FG","i":"Normal","p":"1111110","ic":"💧","pc":"Engine"}]},{"name":"b136ef86f1179bfb58e01aa587e354fb","fluids":[{"n":"Soul 2.0 MPI (2019- )","c":"G4NA","i":"Normal","p":"1111110","ic":"💧","pc":"Engine"}]}]},{"name":"ef3a5e626829442d","types":[{"name":"201d4f3158b0fd5b","fluids":[{"n":"Sportage 1.6 T-GDI AWD (2016-2018)","c":"G4FJ","i":"Normal","p":"1112106","ic":"💧","pc":"Engine"}]},{"name":"27e5c64e8edb2114","fluids":[{"n":"Sportage 2.0 MPI AWD (2016-2018)","c":"G4NA","i":"Normal","p":"1111110","ic":"💧","pc":"Engine"}]},{"name":"287916e6dfaec30e","fluids":[{"n":"Sportage 2.0 AWD (2016-2018)","c":"D4HA","i":"Normal","p":"1111100","ic":"💧","pc":"Engine"}]},{"name":"37ede5b292c5aa92f68a3cd677fb9ea3","fluids":[{"n":"Sportage 2.0 MPI AWD (2016-2018)","c":"G4NA","i":"Normal","p":"1111110","ic":"💧","pc":"Engine"}]},{"name":"44041c6f016580ff","fluids":[{"n":"Sportage 2.0 AWD DPF (2019- )","c":"D4HA","i":"Normal","p":"1111106","ic":"💧","pc":"Engine"}]},{"name":"486216b3b4ac8dd2","fluids":[{"n":"Sportage 2.0 MPI (2019- )","c":"G4NA","i":"Normal","p":"1111110","ic":"💧","pc":"Engine"}]},{"name":"4b98b1ab5ddaa4fcfd64d42308b557a4","fluids":[{"n":"Sportage 2.0 AWD DPF (2016-2018)","c":"D4HA","i":"Normal","p":"1111137","ic":"💧","pc":"Engine"}]},{"name":"62dfdd845e1b600d7a068060312b1ffa","fluids":[{"n":"Sportage 1.6 T-GDI AWD (2016-2018)","c":"G4FJ","i":"Normal","p":"1111122","ic":"💧","pc":"Engine"}]},{"name":"6c248f44eb2efd2c","fluids":[{"n":"Sportage 2.0 AWD DPF (2016-2018)","c":"D4HA","i":"Normal","p":"1111106","ic":"💧","pc":"Engine"}]},{"name":"6d91bc91a4ba4f82","fluids":[{"n":"Sportage 2.0 MPI AWD (2019- )","c":"G4NA","i":"Normal","p":"1111110","ic":"💧","pc":"Engine"}]},{"name":"71f2b8f07694ab3fb5a68c0d18348e4d","fluids":[{"n":"Sportage 2.0 AWD (2019- )","c":"D4HA","i":"Normal","p":"1111100","ic":"💧","pc":"Engine"}]},{"name":"73f0ae25d089fe24a0e8f5176dd57675","fluids":[{"n":"Sportage 2.0 AWD (2016-2018)","c":"D4HA","i":"Normal","p":"1111100","ic":"💧","pc":"Engine"}]},{"name":"7e61e7d693013d7380554cc47e67f527","fluids":[{"n":"Sportage 2.0 AWD DPF (2019- )","c":"D4HA","i":"Normal","p":"1111137","ic":"💧","pc":"Engine"}]},{"name":"85f81ed0bc625252","fluids":[{"n":"Sportage 2.0 MPI (2016-2018)","c":"G4NA","i":"Normal","p":"1111110","ic":"💧","pc":"Engine"}]},{"name":"91847a7fce4fc816a7d35c1ad974ac5e","fluids":[{"n":"Sportage 2.0 MPI AWD (2019- )","c":"G4NA","i":"Normal","p":"1111110","ic":"💧","pc":"Engine"}]},{"name":"965213245a688cef","fluids":[{"n":"Sportage 2.4 GDI AWD (2019- )","c":"Theta II 2.4","i":"Normal","p":"1112106","ic":"💧","pc":"Engine"}]},{"name":"a1c0e6bb331db1cb","fluids":[{"n":"Sportage 2.0 AWD (2019- )","c":"D4HA","i":"Normal","p":"1111100","ic":"💧","pc":"Engine"}]},{"name":"b009277a52abca6b6822873dd59405a7","fluids":[{"n":"Sportage 2.0 MPI (2016-2018)","c":"G4NA","i":"Normal","p":"1111110","ic":"💧","pc":"Engine"}]},{"name":"b906cb6196ccad36286417b1eeefdddf","fluids":[{"n":"Sportage 2.4 GDI AWD (2019- )","c":"Theta II 2.4","i":"Normal","p":"1111122","ic":"💧","pc":"Engine"}]},{"name":"e235bb826e7fec5ccbe727315e24b2c0","fluids":[{"n":"Sportage 2.0 MPI (2019- )","c":"G4NA","i":"Normal","p":"1111110","ic":"💧","pc":"Engine"}]}]},{"name":"f0ab796e11597aea","types":[{"name":"195d8d504b357459","fluids":[{"n":"ceed 1.6 MPI (2018- )","c":"G4FC","i":"Normal","p":"1111110","ic":"💧","pc":"Engine"}]},{"name":"74e3d2d6cfc30f4371b475ed918d378b","fluids":[{"n":"Ceed 1.6 MPI (2018- )","c":"G4FC","i":"Normal","p":"1111110","ic":"💧","pc":"Engine"}]}]},{"name":"ff779c7b428a2966","types":[{"name":"2f4feafb9e742fe0dd5b406cce576bff","fluids":[{"n":"K5 2.0 MPI (2020- )","c":"G4NA","i":"Normal","p":"1111110","ic":"💧","pc":"Engine"}]},{"name":"65dcc29f09e41ff6a80527a4b88eac08","fluids":[{"n":"K5 2.5 GDI (2020- )","c":"G4KN","i":"Normal","p":"1111109","ic":"💧","pc":"Engine"}]},{"name":"ceea7b849fd4233a","fluids":[{"n":"K5 2.0 MPI (2020- )","c":"G4NA","i":"Normal","p":"1111110","ic":"💧","pc":"Engine"}]},{"name":"d47d47bff58e4e80","fluids":[{"n":"K5 2.5 GDI (2020- )","c":"G4KN","i":"Normal","p":"1111109","ic":"💧","pc":"Engine"}]}]}]}