{"make":"BYD","models":[{"name":"Atto 3 (2022- )","types":[{"name":"Atto 3 (60,5 kWh) (2022- )","fluids":[{"n":"Reduction gearbox","c":"Capacity 0.55-0.65 litre","i":"Change 48000 km/ 24 months","p":"Ultra1Plus ATF Dexron III/Mercon Multi-Purpose","ic":"⚙️","pc":"44927","ravenol":"RAVENOL ATF Dexron F III","u1pSku":"UCDIIIMMPL"},{"n":"Hydraulic brake system","c":"Capacity 1-1.1 litre","i":"Change 40000 km/ 24 months","p":"Special Product","ic":"🛑"},{"n":"Cooling system","c":"Capacity 3.8-4 litre","i":"Change 100000 km/ 48 months","p":"Special Product","ic":"❄️"}]}]},{"name":"Tang (2021- )","types":[{"name":"Tang (86,4 kWh) (2021- )","fluids":[{"n":"Reduction gearbox","c":"Capacity 0.95 litre (Rear), Capacity 0.85 litre (Front)","i":"Change 48000 km/ 24 months","p":"Ultra1Plus ATF Dexron III/Mercon Multi-Purpose","ic":"⚙️","pc":"44927","ravenol":"RAVENOL ATF Dexron F III","u1pSku":"UCDIIIMMPL"},{"n":"Hydraulic brake system","c":"Capacity 1.15 litre","i":"Change 40000 km/ 24 months","p":"Special Product","ic":"🛑"},{"n":"Cooling system, high voltage battery","c":"Capacity 9.3 litre","i":"Change 100000 km/ 24 months","p":"Special Product","ic":"❄️"},{"n":"Cooling system, power electronics","c":"Capacity 5 litre","i":"Change 100000 km/ 48 months","p":"Special Product","ic":"❄️"},{"n":"Airconditioning system","c":"Capacity 700-740 grams","i":"","p":"Special Product","ic":"💧","pc":"R-1234yf"}]}]}]}