{"make":"New Holland (Tractors)","models":[{"name":"Workmaster 25S","types":[{"name":"25 hp 3-Cylinder Diesel","fluids":[{"n":"Engine Oil","c":"3.5L","i":"200 hours","p":"Heavy Duty Diesel 10W-30","ic":"oil","pc":"Motor Oil"},{"n":"Hydraulic Fluid","c":"10.0L","i":"400 hours","p":"AW 46 Hydraulic Oil","ic":"transmission","pc":"Hydraulic Fluid"},{"n":"Engine Coolant","c":"3.5L","i":"2 years","p":"Heavy Duty Extended Life Coolant","ic":"coolant","pc":"Coolant"},{"n":"Chassis Grease","c":"As needed","i":"50 hours / weekly","p":"NLGI #2 Multi-Purpose Grease","ic":"oil","pc":"Grease"}]}]},{"name":"Workmaster 55","types":[{"name":"55 hp 3-Cylinder Diesel","fluids":[{"n":"Engine Oil","c":"6.0L","i":"250 hours","p":"Heavy Duty Diesel 15W-40","ic":"oil","pc":"Motor Oil"},{"n":"Hydraulic Fluid","c":"22.0L","i":"500 hours","p":"AW 46 Hydraulic Oil","ic":"transmission","pc":"Hydraulic Fluid"},{"n":"Engine Coolant","c":"6.0L","i":"2 years","p":"Heavy Duty Extended Life Coolant","ic":"coolant","pc":"Coolant"},{"n":"Chassis Grease","c":"As needed","i":"50 hours / weekly","p":"NLGI #2 Multi-Purpose Grease","ic":"oil","pc":"Grease"}]}]},{"name":"Workmaster 75","types":[{"name":"75 hp 4-Cylinder Diesel","fluids":[{"n":"Engine Oil","c":"7.5L","i":"250 hours","p":"Heavy Duty Diesel 15W-40","ic":"oil","pc":"Motor Oil"},{"n":"Hydraulic Fluid","c":"30.0L","i":"500 hours","p":"AW 46 Hydraulic Oil","ic":"transmission","pc":"Hydraulic Fluid"},{"n":"Engine Coolant","c":"8.0L","i":"2 years","p":"Heavy Duty Extended Life Coolant","ic":"coolant","pc":"Coolant"},{"n":"Transmission Fluid","c":"14.0L","i":"1,000 hours","p":"Shuttle Fluid","ic":"transmission","pc":"Transmission Fluid"},{"n":"Chassis Grease","c":"As needed","i":"50 hours / weekly","p":"NLGI #2 Multi-Purpose Grease","ic":"oil","pc":"Grease"}]}]},{"name":"T5.120","types":[{"name":"117 hp 4-Cylinder Diesel","fluids":[{"n":"Engine Oil","c":"10.0L","i":"500 hours","p":"Heavy Duty Diesel 15W-40","ic":"oil","pc":"Motor Oil"},{"n":"Hydraulic Fluid","c":"50.0L","i":"1,000 hours","p":"AW 46 Hydraulic Oil","ic":"transmission","pc":"Hydraulic Fluid"},{"n":"Engine Coolant","c":"12.0L","i":"2 years","p":"Heavy Duty Extended Life Coolant","ic":"coolant","pc":"Coolant"},{"n":"Transmission Fluid","c":"18.0L","i":"1,500 hours","p":"Electro Command Fluid","ic":"transmission","pc":"Transmission Fluid"},{"n":"Diesel Exhaust Fluid (DEF)","c":"10.0L","i":"Refill as needed","p":"DEF / AdBlue","ic":"coolant","pc":"DEF"},{"n":"Chassis Grease","c":"As needed","i":"50 hours / weekly","p":"NLGI #2 Multi-Purpose Grease","ic":"oil","pc":"Grease"}]}]},{"name":"T6.180","types":[{"name":"175 hp 6-Cylinder Diesel","fluids":[{"n":"Engine Oil","c":"14.0L","i":"500 hours","p":"Heavy Duty Diesel 15W-40","ic":"oil","pc":"Motor Oil"},{"n":"Hydraulic Fluid","c":"65.0L","i":"1,000 hours","p":"AW 46 Hydraulic Oil","ic":"transmission","pc":"Hydraulic Fluid"},{"n":"Engine Coolant","c":"16.0L","i":"2 years","p":"Heavy Duty Extended Life Coolant","ic":"coolant","pc":"Coolant"},{"n":"Transmission Fluid","c":"20.0L","i":"1,500 hours","p":"Auto Command CVT Fluid","ic":"transmission","pc":"Transmission Fluid"},{"n":"Diesel Exhaust Fluid (DEF)","c":"15.0L","i":"Refill as needed","p":"DEF / AdBlue","ic":"coolant","pc":"DEF"},{"n":"Chassis Grease","c":"As needed","i":"50 hours / weekly","p":"NLGI #2 Multi-Purpose Grease","ic":"oil","pc":"Grease"}]}]},{"name":"T7.315","types":[{"name":"315 hp 6-Cylinder Diesel","fluids":[{"n":"Engine Oil","c":"22.0L","i":"500 hours","p":"Heavy Duty Diesel 15W-40","ic":"oil","pc":"Motor Oil"},{"n":"Hydraulic Fluid","c":"90.0L","i":"1,500 hours","p":"AW 46 Hydraulic Oil","ic":"transmission","pc":"Hydraulic Fluid"},{"n":"Engine Coolant","c":"25.0L","i":"2 years","p":"Heavy Duty Extended Life Coolant","ic":"coolant","pc":"Coolant"},{"n":"Transmission Fluid","c":"28.0L","i":"2,000 hours","p":"Auto Command CVT Fluid","ic":"transmission","pc":"Transmission Fluid"},{"n":"Diesel Exhaust Fluid (DEF)","c":"25.0L","i":"Refill as needed","p":"DEF / AdBlue","ic":"coolant","pc":"DEF"},{"n":"Chassis Grease","c":"As needed","i":"50 hours / weekly","p":"NLGI #2 Multi-Purpose Grease","ic":"oil","pc":"Grease"}]}]},{"name":"T9.565","types":[{"name":"565 hp 6-Cylinder Diesel","fluids":[{"n":"Engine Oil","c":"36.0L","i":"500 hours","p":"Heavy Duty Diesel 15W-40","ic":"oil","pc":"Motor Oil"},{"n":"Hydraulic Fluid","c":"120.0L","i":"1,500 hours","p":"AW 46 Hydraulic Oil","ic":"transmission","pc":"Hydraulic Fluid"},{"n":"Engine Coolant","c":"38.0L","i":"2 years","p":"Heavy Duty Extended Life Coolant","ic":"coolant","pc":"Coolant"},{"n":"Transmission Fluid","c":"35.0L","i":"2,000 hours","p":"Powershift Fluid","ic":"transmission","pc":"Transmission Fluid"},{"n":"Diesel Exhaust Fluid (DEF)","c":"40.0L","i":"Refill as needed","p":"DEF / AdBlue","ic":"coolant","pc":"DEF"},{"n":"Chassis Grease","c":"As needed","i":"50 hours / weekly","p":"NLGI #2 Multi-Purpose Grease","ic":"oil","pc":"Grease"}]}]}]}